cuit_alore_duoyuan/__init__.py
cuit_alore_duoyuan/__main__.py
cuit_alore_duoyuan/data/1-1.txt
cuit_alore_duoyuan/data/1-2.txt
cuit_alore_duoyuan/data/2-1.txt
cuit_alore_duoyuan/data/2-2.txt
cuit_alore_duoyuan/data/2-3.txt
cuit_alore_duoyuan/data/2-4.txt
cuit_alore_duoyuan/data/3-1.txt
cuit_alore_duoyuan/data/help.txt
cuit_alore_duoyuan-0.1.3.dist-info/METADATA
cuit_alore_duoyuan-0.1.3.dist-info/WHEEL
cuit_alore_duoyuan-0.1.3.dist-info/entry_points.txt
cuit_alore_duoyuan-0.1.3.dist-info/top_level.txt
cuit_alore_duoyuan-0.1.3.dist-info/RECORD
