Metadata-Version: 2.4
Name: cuit_alore_duoyuan
Version: 0.1.3
Summary: CUIT课堂代码库
Author: Alore
Classifier: Programming Language :: Python :: 3
Classifier: Operating System :: OS Independent
Requires-Python: >=3.6
Dynamic: author
Dynamic: classifier
Dynamic: description-content-type
Dynamic: requires-python
Dynamic: summary
